northguard/__init__.py
northguard-0.0.1.dist-info/METADATA
northguard-0.0.1.dist-info/WHEEL
northguard-0.0.1.dist-info/RECORD
