Metadata-Version: 2.3
Name: northguard
Version: 0.0.1
Summary: A Python client for a pubsub system.
Author: jonb
Requires-Python: >=3.13
Classifier: Programming Language :: Python :: 3
Classifier: Programming Language :: Python :: 3.13
